doltcli/__init__.py
doltcli/dolt.py
doltcli/misc_mixin.py
doltcli/types.py
doltcli/utils.py
doltcli-1.1.10.dist-info/LICENSE
doltcli-1.1.10.dist-info/WHEEL
doltcli-1.1.10.dist-info/METADATA
doltcli-1.1.10.dist-info/RECORD
